{"cameraMode":{"drawMode":0,"name":"Shaded","section":"Shading Mode"},"sceneLighting":false,"audioPlay":false,"sceneViewState":{"showFog":true,"showMaterialUpdate":false,"showSkybox":false,"showFlares":true,"showImageEffects":true,"showParticleSystems":true},"in2DMode":false,"pivot":{"x":-7.843127727508545,"y":1.5359957218170167,"z":1.9645376205444337},"rotation":{"x":0.12739460170269013,"y":-0.042836744338274,"z":0.005437275394797325,"w":0.991276741027832},"size":6.045836925506592,"orthographic":false}